{
  "id": "Weekly_beetle_community_abundance",
  "description": "All models for the Weekly_beetle_community_abundance variable. The variable description is as follows: Total number of carabid individuals per trap-night, estimated each week of the year at each NEON site",
  "stac_version": "1.0.0",
  "license": "CC0-1.0",
  "stac_extensions": [
    "https://stac-extensions.github.io/table/v1.2.0/schema.json"
  ],
  "type": "Collection",
  "links": [
    {
      "rel": "item",
      "type": "application/json",
      "href": "./models/tg_humidity_lm_all_sites.json"
    },
    {
      "rel": "item",
      "type": "application/json",
      "href": "./models/tg_precip_lm.json"
    },
    {
      "rel": "item",
      "type": "application/json",
      "href": "./models/tg_randfor.json"
    },
    {
      "rel": "item",
      "type": "application/json",
      "href": "./models/tg_precip_lm_all_sites.json"
    },
    {
      "rel": "item",
      "type": "application/json",
      "href": "./models/tg_temp_lm_all_sites.json"
    },
    {
      "rel": "item",
      "type": "application/json",
      "href": "./models/tg_tbats.json"
    },
    {
      "rel": "item",
      "type": "application/json",
      "href": "./models/tg_arima.json"
    },
    {
      "rel": "item",
      "type": "application/json",
      "href": "./models/tg_ets.json"
    },
    {
      "rel": "item",
      "type": "application/json",
      "href": "./models/tg_XGBoost.json"
    },
    {
      "rel": "item",
      "type": "application/json",
      "href": "./models/tg_humidity_lm.json"
    },
    {
      "rel": "item",
      "type": "application/json",
      "href": "./models/tg_lasso.json"
    },
    {
      "rel": "item",
      "type": "application/json",
      "href": "./models/tg_temp_lm.json"
    },
    {
      "rel": "item",
      "type": "application/json",
      "href": "./models/tg_SVM.json"
    },
    {
      "rel": "item",
      "type": "application/json",
      "href": "./models/tg_elasticNet.json"
    },
    {
      "rel": "parent",
      "type": "application/json",
      "href": "../collection.json"
    },
    {
      "rel": "root",
      "type": "application/json",
      "href": "../collection.json"
    },
    {
      "rel": "self",
      "type": "application/json",
      "href": "collection.json"
    },
    {
      "rel": "cite-as",
      "href": "https://doi.org/10.1002/fee.2616"
    },
    {
      "rel": "about",
      "href": "https://projects.ecoforecast.org/neon4cast-docs/",
      "type": "text/html",
      "title": "NEON Ecological Forecasting Challenge Documentation"
    },
    {
      "rel": "describedby",
      "href": "https://projects.ecoforecast.org/neon4cast-docs/",
      "title": "NEON Ecological Forecasting Challenge",
      "type": "text/html"
    }
  ],
  "title": "Weekly_beetle_community_abundance",
  "extent": {
    "spatial": {
      "bbox": [
        [-156.6194, 17.9696, -66.8687, 71.2824]
      ]
    },
    "temporal": {
      "interval": [
        [
          "2021-05-17T00:00:00Z",
          "2025-11-10T00:00:00Z"
        ]
      ]
    }
  },
  "table:columns": [
    {
      "name": "reference_datetime",
      "type": "timestamp[us, tz=UTC]",
      "description": "datetime that the forecast was initiated (horizon = 0)"
    },
    {
      "name": "site_id",
      "type": "string",
      "description": "For forecasts that are not on a spatial grid, use of a site dimension that maps to a more detailed geometry (points, polygons, etc.) is allowable. In general this would be documented in the external metadata (e.g., alook-up table that provides lon and lat); however in netCDF this could be handled by the CF Discrete Sampling Geometry data model."
    },
    {
      "name": "datetime",
      "type": "timestamp[us, tz=UTC]",
      "description": "datetime of the forecasted value (ISO 8601)"
    },
    {
      "name": "family",
      "type": "string",
      "description": "For ensembles: “ensemble.” Default value if unspecified For probability distributions: Name of the statistical distribution associated with the reported statistics. The “sample” distribution is synonymous with “ensemble.” For summary statistics: “summary.”If this dimension does not vary, it is permissible to specify family as a variable attribute if the file format being used supports this (e.g.,netCDF)."
    },
    {
      "name": "pub_datetime",
      "type": "timestamp[us, tz=UTC]",
      "description": "datetime that forecast was submitted"
    },
    {
      "name": "observation",
      "type": "double",
      "description": "observed value for variable"
    },
    {
      "name": "crps",
      "type": "double",
      "description": "crps forecast score"
    },
    {
      "name": "logs",
      "type": "double",
      "description": "logs forecast score"
    },
    {
      "name": "mean",
      "type": "double",
      "description": "mean forecast prediction"
    },
    {
      "name": "median",
      "type": "double",
      "description": "median forecast prediction"
    },
    {
      "name": "sd",
      "type": "double",
      "description": "standard deviation forecasts"
    },
    {
      "name": "quantile97.5",
      "type": "double",
      "description": "upper 97.5 percentile value of forecast"
    },
    {
      "name": "quantile02.5",
      "type": "double",
      "description": "upper 2.5 percentile value of forecast"
    },
    {
      "name": "quantile90",
      "type": "double",
      "description": "upper 90 percentile value of forecast"
    },
    {
      "name": "quantile10",
      "type": "double",
      "description": "upper 10 percentile value of forecast"
    },
    {
      "name": "duration",
      "type": "string",
      "description": "temporal duration of forecast (hourly = PT1H, daily = P1D, etc.); follows ISO 8601 duration convention"
    },
    {
      "name": "model_id",
      "type": "string",
      "description": "unique model identifier"
    },
    {
      "name": "project_id",
      "type": "string",
      "description": "unique project identifier"
    }
  ],
  "assets": {
    "data": {
      "href": "\"s3://anonymous@bio230014-bucket01/challenges/scores/bundled-parquet/project_id=neon4cast/duration=Weekly/variable=abundance?endpoint_override=sdsc.osn.xsede.org\"",
      "type": "application/x-parquet",
      "title": "Database Access",
      "roles": [
        "data"
      ],
      "description": "Use `arrow` for remote access to the database. This R code will return results for forecasts of the variable by the specific model .\n\n### R\n\n```{r}\n# Use code below\n\nall_results <- arrow::open_dataset(\"s3://anonymous@bio230014-bucket01/challenges/scores/bundled-parquet/project_id=neon4cast/duration=Weekly/variable=abundance?endpoint_override=sdsc.osn.xsede.org\")\ndf <- all_results |> dplyr::collect()\n\n```\n       \n\nYou can use dplyr operations before calling `dplyr::collect()` to `summarise`, `select` columns, and/or `filter` rows prior to pulling the data into a local `data.frame`. Reducing the data that is pulled locally will speed up the data download speed and reduce your memory usage.\n\n\n"
    },
    "thumbnail": {
      "href": "https://www.neonscience.org/sites/default/files/styles/max_width_1170px/public/image-content-images/Beetles_pinned.jpg",
      "type": "image/JPEG",
      "roles": [
        "thumbnail"
      ],
      "title": "Thumbnail Image"
    }
  }
}
